README.md
setup.cfg
setup.py
AwesomeBuild/JobManager.py
AwesomeBuild/Rule.py
AwesomeBuild/RulesTree.py
AwesomeBuild/RunStat.py
AwesomeBuild/Stats.py
AwesomeBuild/StatusFile.py
AwesomeBuild/Trigger.py
AwesomeBuild/TriggerStatus.py
AwesomeBuild/Updater.py
AwesomeBuild/__init__.py
AwesomeBuild/__main__.py
AwesomeBuild/importer.py
AwesomeBuild.egg-info/PKG-INFO
AwesomeBuild.egg-info/SOURCES.txt
AwesomeBuild.egg-info/dependency_links.txt
AwesomeBuild.egg-info/entry_points.txt
AwesomeBuild.egg-info/requires.txt
AwesomeBuild.egg-info/top_level.txt