Metadata-Version: 2.1
Name: AwesomeBuild
Version: 2.5.0
Summary: Awesome build manager to replace Makefiles. It allows very fast building!
Home-page: https://github.com/ski7777/AwesomeBuild
Author: Raphael Jacob
Author-email: r.jacob2002@gmail.com
License: GPLv3
Platform: UNKNOWN
